mtnlpmodel/__init__.py
mtnlpmodel/core.py
mtnlpmodel/fine_tuning.py
mtnlpmodel/train.py
mtnlpmodel/server/__init__.py
mtnlpmodel/server/evaluation/__init__.py
mtnlpmodel/server/evaluation/evaluation.py
mtnlpmodel/server/evaluation/run_evaluation.py
mtnlpmodel/server/inference/__init__.py
mtnlpmodel/server/inference/inference.py
mtnlpmodel/server/inference/run_inference.py
mtnlpmodel/server/semantic_similarity/__init__.py
mtnlpmodel/server/semantic_similarity/calc_semantic_similarity.py
mtnlpmodel/utils/__init__.py
mtnlpmodel/utils/ctrldir_util.py
mtnlpmodel/utils/decoder_util.py
mtnlpmodel/utils/deliverablemodel_util.py
mtnlpmodel/utils/input_process_util.py
mtnlpmodel/utils/io_utils.py
mtnlpmodel/utils/loss_func_util.py
mtnlpmodel/utils/lrset_util.py
mtnlpmodel/utils/model_util.py
mtnlpmodel/utils/optimizer_util.py
mtnlpmodel/utils/triplet_loss_util.py
mtnlpmodel-0.0.4.dist-info/LICENSE
mtnlpmodel-0.0.4.dist-info/METADATA
mtnlpmodel-0.0.4.dist-info/WHEEL
mtnlpmodel-0.0.4.dist-info/top_level.txt
mtnlpmodel-0.0.4.dist-info/RECORD
